chehro
