Metadata-Version: 2.1
Name: chehro
Version: 0.0.4
Summary: A face detection system with mediapipe backend.
Home-page: https://github.com/prp-e/chehro
Author: Muhammadreza Haghiri
Author-email: <haghiri75@gmail.com>
License: MIT
Keywords: face detection,cv,computer-vision
Platform: UNKNOWN
Classifier: Development Status :: 1 - Planning
Classifier: Intended Audience :: Developers
Classifier: Programming Language :: Python :: 3
Classifier: Operating System :: Unix
Classifier: Operating System :: MacOS :: MacOS X
Classifier: Operating System :: Microsoft :: Windows
